ZenoMapper/Types.py
ZenoMapper/__init__.py
ZenoMapper-0.25.18.dist-info/LICENSE
ZenoMapper-0.25.18.dist-info/METADATA
ZenoMapper-0.25.18.dist-info/WHEEL
ZenoMapper-0.25.18.dist-info/top_level.txt
ZenoMapper-0.25.18.dist-info/RECORD
